fructose/__init__.py
fructose/ai.py
fructose/function_helpers.py
fructose/llm_function_handler.py
fructose/type_parser.py
fructose/types.py
fructose/templates/__init__.py
fructose/templates/chain_of_thought_json.jinja
fructose/templates/chain_of_thought_prompt.jinja
fructose/templates/default_prompt.jinja
fructose/templates/human_prompt.jinja
fructose/templates/__pycache__/__init__.cpython-39.pyc
fructose-0.0.13.dist-info/LICENSE
fructose-0.0.13.dist-info/METADATA
fructose-0.0.13.dist-info/WHEEL
fructose-0.0.13.dist-info/top_level.txt
fructose-0.0.13.dist-info/RECORD
