Metadata-Version: 2.1
Name: fructose
Version: 0.0.13
Summary: A package for strongly-typed LLM function calling
Home-page: https://github.com/bananaml/fructose
Author: Banana
Author-email: erik@banana.dev
License: UNKNOWN
Platform: UNKNOWN
License-File: LICENSE
Requires-Dist: openai
Requires-Dist: Jinja2
